[
  {
    "title": "技术卓越",
    "description": "New clients recieve an obligation free consultation.",
    "image": "images/features/noun_branding_1885335.svg"
  },
  {
    "title": "服务专业",
    "description": "All members of our team are certified accountants.",
    "image": "images/features/noun_The Process_1885341.svg"
  },
  {
    "title": "经验丰富",
    "description": "Lorem markdownum Achaica revolutaque amore, penitus puppes nec furit, clipeus fatetur, mira inter accedere.",
    "image": "images/features/noun_3d modeling_1885342.svg"
  }
]
